killtimer/__init__.py
killtimer/alsa_utils.py
killtimer/main.py
killtimer/stats.py
killtimer-0.4.0.dist-info/METADATA
killtimer-0.4.0.dist-info/WHEEL
killtimer-0.4.0.dist-info/entry_points.txt
killtimer-0.4.0.dist-info/RECORD
